waifu2x_ncnn_py-2.0.0.dist-info/METADATA
waifu2x_ncnn_py-2.0.0.dist-info/WHEEL
waifu2x_ncnn_py-2.0.0.dist-info/licenses/LICENSE
waifu2x_ncnn_py/__init__.py
waifu2x_ncnn_py/models/models-cunet/noise0_model.bin
waifu2x_ncnn_py/models/models-cunet/noise0_model.param
waifu2x_ncnn_py/models/models-cunet/noise0_scale2.0x_model.bin
waifu2x_ncnn_py/models/models-cunet/noise0_scale2.0x_model.param
waifu2x_ncnn_py/models/models-cunet/noise1_model.bin
waifu2x_ncnn_py/models/models-cunet/noise1_model.param
waifu2x_ncnn_py/models/models-cunet/noise1_scale2.0x_model.bin
waifu2x_ncnn_py/models/models-cunet/noise1_scale2.0x_model.param
waifu2x_ncnn_py/models/models-cunet/noise2_model.bin
waifu2x_ncnn_py/models/models-cunet/noise2_model.param
waifu2x_ncnn_py/models/models-cunet/noise2_scale2.0x_model.bin
waifu2x_ncnn_py/models/models-cunet/noise2_scale2.0x_model.param
waifu2x_ncnn_py/models/models-cunet/noise3_model.bin
waifu2x_ncnn_py/models/models-cunet/noise3_model.param
waifu2x_ncnn_py/models/models-cunet/noise3_scale2.0x_model.bin
waifu2x_ncnn_py/models/models-cunet/noise3_scale2.0x_model.param
waifu2x_ncnn_py/models/models-cunet/scale2.0x_model.bin
waifu2x_ncnn_py/models/models-cunet/scale2.0x_model.param
waifu2x_ncnn_py/models/models-upconv_7_anime_style_art_rgb/noise0_scale2.0x_model.bin
waifu2x_ncnn_py/models/models-upconv_7_anime_style_art_rgb/noise0_scale2.0x_model.param
waifu2x_ncnn_py/models/models-upconv_7_anime_style_art_rgb/noise1_scale2.0x_model.bin
waifu2x_ncnn_py/models/models-upconv_7_anime_style_art_rgb/noise1_scale2.0x_model.param
waifu2x_ncnn_py/models/models-upconv_7_anime_style_art_rgb/noise2_scale2.0x_model.bin
waifu2x_ncnn_py/models/models-upconv_7_anime_style_art_rgb/noise2_scale2.0x_model.param
waifu2x_ncnn_py/models/models-upconv_7_anime_style_art_rgb/noise3_scale2.0x_model.bin
waifu2x_ncnn_py/models/models-upconv_7_anime_style_art_rgb/noise3_scale2.0x_model.param
waifu2x_ncnn_py/models/models-upconv_7_anime_style_art_rgb/scale2.0x_model.bin
waifu2x_ncnn_py/models/models-upconv_7_anime_style_art_rgb/scale2.0x_model.param
waifu2x_ncnn_py-2.0.0.dist-info/RECORD
